Metadata-Version: 2.1
Name: odoo-addon-l10n_br_setup_tests
Version: 16.0.1.0.1
Requires-Python: >=3.10
Requires-Dist: odoo-addon-account_usability>=16.0dev,<16.1dev
Requires-Dist: odoo-addon-base_technical_features>=16.0dev,<16.1dev
Requires-Dist: odoo-addon-web_responsive>=16.0dev,<16.1dev
Requires-Dist: odoo-addon-web_theme_classic>=16.0dev,<16.1dev
Requires-Dist: odoo>=16.0a,<16.1dev
Summary: Modules for Odoo's Brazil-focused usability with integration tests.
Home-page: https://github.com/OCA/l10n-brazil
License: AGPL-3
Author: Engenere, Odoo Community Association (OCA)
Author-email: support@odoo-community.org
Classifier: Programming Language :: Python
Classifier: Framework :: Odoo
Classifier: Framework :: Odoo :: 16.0
Classifier: License :: OSI Approved :: GNU Affero General Public License v3
Classifier: Development Status :: 4 - Beta
